adspower/.DS_Store
adspower/__init__.py
adspower/_api_entity.py
adspower/_base_category.py
adspower/_base_group.py
adspower/_base_http_client.py
adspower/_base_profile_api.py
adspower/async_api/__init__.py
adspower/async_api/_base_profile.py
adspower/async_api/category.py
adspower/async_api/group.py
adspower/async_api/http_client.py
adspower/async_api/playwright/__init__.py
adspower/async_api/playwright/profile.py
adspower/async_api/profile_api.py
adspower/async_api/selenium/__init__.py
adspower/async_api/selenium/profile.py
adspower/exceptions.py
adspower/sync_api/__init__.py
adspower/sync_api/_base_profile.py
adspower/sync_api/category.py
adspower/sync_api/group.py
adspower/sync_api/http_client.py
adspower/sync_api/playwright/__init__.py
adspower/sync_api/playwright/profile.py
adspower/sync_api/profile_api.py
adspower/sync_api/selenium/__init__.py
adspower/sync_api/selenium/profile.py
adspower/types.py
adspower/utils.py
adspower-2.1.0.dist-info/LICENSE
adspower-2.1.0.dist-info/METADATA
adspower-2.1.0.dist-info/WHEEL
adspower-2.1.0.dist-info/RECORD
