Metadata-Version: 2.1
Name: adspower
Version: 2.1.0
Summary: The package for interacting with API of anti-detect browser AdsPower.
Home-page: https://github.com/CrocoFactory/adspower
License: MIT
Author: Alexey
Author-email: axbelenkov@gmail.com
Requires-Python: >=3.9,<4.0
Classifier: Development Status :: 5 - Production/Stable
Classifier: Intended Audience :: Developers
Classifier: License :: OSI Approved :: MIT License
Classifier: Operating System :: OS Independent
Classifier: Programming Language :: Python :: 3
Classifier: Programming Language :: Python :: 3.9
Classifier: Programming Language :: Python :: 3.10
Classifier: Programming Language :: Python :: 3.11
Classifier: Programming Language :: Python :: 3.12
Classifier: Programming Language :: Python :: 3 :: Only
Classifier: Topic :: Software Development :: Libraries :: Python Modules
Classifier: Typing :: Typed
Provides-Extra: playwright
Provides-Extra: selenium
Requires-Dist: httpx (>=0.27.0,<0.28.0)
Requires-Dist: playwright (>=1.42.0,<2.0.0) ; extra == "playwright"
Requires-Dist: selenium (>=4.16.0,<5.0.0) ; extra == "selenium"
Project-URL: Repository, https://github.com/CrocoFactory/adspower
